shein_django_jaeger_middleware/__init__.py
shein_django_jaeger_middleware/middleware.py
shein_django_jaeger_middleware/requests.py
shein_django_jaeger_middleware-0.2.7.dist-info/LICENSE
shein_django_jaeger_middleware-0.2.7.dist-info/METADATA
shein_django_jaeger_middleware-0.2.7.dist-info/WHEEL
shein_django_jaeger_middleware-0.2.7.dist-info/top_level.txt
shein_django_jaeger_middleware-0.2.7.dist-info/RECORD
