Metadata-Version: 2.1
Name: shein-django-jaeger-middleware
Version: 0.2.7
Summary: python(django) tracing middleware tool: django-jaeger-middleware
Home-page: https://github.com/lpf32/shein-django-jaeger-middleware
Author: zhangpanpan
Author-email: zhpan188@gmail.com
License: MIT
Keywords: django,jaeger,jaegertracing,requests
Platform: UNKNOWN
Classifier: Framework :: Django
Classifier: Programming Language :: Python :: 3
Classifier: License :: OSI Approved :: MIT License
Classifier: Operating System :: OS Independent
Requires-Python: >=3.6
Requires-Dist: jaeger-client
Requires-Dist: opentracing
Requires-Dist: requests
